tortoise_database_url-0.5.0.dist-info/METADATA
tortoise_database_url-0.5.0.dist-info/WHEEL
tortoise_database_url-0.5.0.dist-info/entry_points.txt
tortoise_database_url/__init__.py
tortoise_database_url/_main.py
tortoise_database_url/py.typed
tortoise_database_url-0.5.0.dist-info/RECORD
