Metadata-Version: 2.1
Name: tortoise-database-url
Version: 0.5.0
Summary: Make it easy to generate database url.
Keywords: database_url,tortoise-orm
Author-Email: Waket Zheng <waketzheng@gmail.com>
Project-URL: homepage, https://github.com/waketzheng/database-url
Project-URL: repository, https://github.com/waketzheng/database-url.git
Requires-Python: >=3.9
Requires-Dist: asynctor>=0.8.7
